Workbook

Sheet P&L Input
A1: P&L Statement
A2: (in thousands) | B2: 2018 Act | C2: 2019 Act | D2: 2020 Act
A3: Revenues | B3: 15794341 | C3: 20156447 | D3: 24996056
A4: Cost of revenues | B4: 9967538 | C4: 12440213 | D4: 15276319
A5: Marketing | B5: 2369469 | C5: 2652462 | D5: 2228362
A6: Technology and development | B6: 1221814 | C6: 1545149 | D6: 1829600
A7: General and administrative | B7: 630294 | C7: 914369 | D7: 1076486
A8: Operating income | B8: 1605226 | C8: 2604254 | D8: 4585289
A9: Other income (expense):
A10: Interest | B10: -420493 | C10: -626023 | D10: -767499
A11: Interest and other income (expense) | B11: 41725 | C11: 84000 | D11: -618441
A12: Income before income taxes | B12: 1226458 | C12: 2062231 | D12: 3199349
A13: Provision for income taxes | B13: -15216 | C13: -195315 | D13: -437954
A14: Net income | B14: 1211242 | C14: 1866916 | D14: 2761395

Sheet Balance Sheet Input
A1: Balance Sheet
A3: (in thousands) | B3: 2018 Act | C3: 2019 Act | D3: 2020 Act
A4: Assets
A5: Current assets:
A6: Cash and cash equivalents | B6: 3794483 | C6: 5018437 | D6: 8205550 | F6: Cashflow
A7: Other current assets | B7: =748466+5151186 -> 5899652 | C7: 1160067 | D7: 1556030 | F7: Other Items
A8: Total current assets | B8: =SUM(B6:B7) -> 9694135 | C8: =SUM(C6:C7) -> 6178504 | D8: =SUM(D6:D7) -> 9761580
A9: Content assets, net | B9: 14951141 | C9: 24504567 | D9: 25383950 | F9: Schedules
A10: Property and equipment, net | B10: 418281 | C10: 565221 | D10: 960183 | F10: Schedules
A11: Other non-current assets | B11: 910843 | C11: 2727420 | D11: 3174646
A12: Total assets | B12: =SUM(B8:B11) -> 25974400 | C12: =SUM(C8:C11) -> 33975712 | D12: =SUM(D8:D11) -> 39280359
A14: Liabilities and Stockholders' Equity
A15: Current liabilities:
A16: Current content liabilities | B16: 4681562 | C16: 4413561 | D16: 4429536
A17: Accounts payable | B17: 562985 | C17: 674347 | D17: 656183 | F17: Other Items
A18: Accrued expenses and other liabilities | B18: 481874 | C18: 843043 | D18: 1102196
A19: Deferred revenue | B19: 760899 | C19: 924745 | D19: 1117992
A20: Short-term debt | B20: 0 | C20: 0 | D20: 499878
A21: Total current liabilities | B21: =SUM(B16:B20) -> 6487320 | C21: =SUM(C16:C20) -> 6855696 | D21: =SUM(D16:D20) -> 7805785
A22: Non-current content liabilities | B22: 3759026 | C22: 3334323 | D22: 2618084
A23: Long-term debt | B23: 10360058 | C23: 14759260 | D23: 15809095
A24: Other non-current liabilities | B24: 129231 | C24: 1444276 | D24: 1982155
A25: Total liabilities | B25: =SUM(B21:B24) -> 20735635 | C25: =SUM(C21:C24) -> 26393555 | D25: =SUM(D21:D24) -> 28215119
A26: Stockholders' equity:
A27: Common stock | B27: 2315988 | C27: 2793929 | D27: 3447698
A28: Treasury stock | C28: 0 | D28: 0
A29: Accumulated other comprehensive income (loss) | B29: -19582 | C29: -23521 | D29: 44398
A30: Retained earnings | B30: 2942359 | C30: 4811749 | D30: 7573144
A31: Total stockholders' equity | B31: =SUM(B27:B30) -> 5238765 | C31: =SUM(C27:C30) -> 7582157 | D31: =SUM(D27:D30) -> 11065240
A32: Total liabilities and stockholders' equity | B32: =B25+B31 -> 25974400 | C32: =C25+C31 -> 33975712 | D32: =D25+D31 -> 39280359

Sheet Revenue Modelling
A1: Revenue Sources
A2: (in thousands) | B2: 2018 Act | C2: 2019 Act | D2: 2020 Act | E2: 2021 FORECASTING | F2: 2022 FORECASTING | G2: 2023 FORECASTING | H2: 2024 FORECASTING
A3: Streaming revenues | B3: =B10+B17+B24+B31 -> 15428752 | C3: =C10+C17+C24+C31 -> 19859230 | D3: =D10+D17+D24+D31 -> 24756675 | E3: =E10+E17+E24+E31 -> 28450601 | F3: =F10+F17+F24+F31 -> 33461472 | G3: =G10+G17+G24+G31 -> 38173270 | H3: =H10+H17+H24+H31 -> 42882608
A4: DVD Revenues | B4: 365589 | C4: 297217 | D4: 239381 | E4: =D4*(1+E5) -> 193705.84 | F4: =E4*(1+F5) -> 156379 | G4: =F4*(1+G5) -> 126393.03 | H4: =G4*(1+H5) -> 102097.1 | L4: NOTES:
A5: Growth % | C5: =(C4/B4-1) -> -0.18701876 | D5: =D4/C4-1 -> -0.19459183 | E5: =AVERAGE(C5:D5) -> -0.19080529 | F5: =AVERAGE(D5:E5) -> -0.19269856 | G5: =AVERAGE(E5:F5) -> -0.19175193 | H5: =AVERAGE(F5:G5) -> -0.19222524 | L5: USA and Canada as the Stabilised market
A6: Total Revenues | B6: =B3+B4 -> 15794341 | C6: =C3+C4 -> 20156447 | D6: =D3+D4 -> 24996056 | E6: =E3+E4 -> 28644307 | F6: =F3+F4 -> 33617851 | G6: =G3+G4 -> 38299663 | H6: =H3+H4 -> 42984705 | L6: Asia Pacific continues to grow at a high rate due to low market penetration
A8: STREAMING REVENUE BIFURCATION | J8: Data Input
A9: Unites States and Canada ( in thousands) | I9: Average Monthly Revenues
A10: Revenues | B10: 8281532 | C10: 10051208 | D10: 11455396 | E10: =E11*E12 -> 11434119 | F10: =F11*F12 -> 12309279 | G10: =G11*G12 -> 13251422 | H10: =H11*H12 -> 14265677 | I10: 2018 | J10: 2019 | K10: 2020
A11: Average yearly revenue per membership | B11: =I11*12 -> 133.92 | C11: =J11*12 -> 150.84 | D11: =K11*12 -> 159.84 | E11: =AVERAGE($B$11:$D$11) -> 148.2 | F11: =AVERAGE($B$11:$D$11) -> 148.2 | G11: =AVERAGE($B$11:$D$11) -> 148.2 | H11: =AVERAGE($B$11:$D$11) -> 148.2 | I11: 11.16 | J11: 12.57 | K11: 13.32
A12: Average Paid membership | B12: =B10/B11 -> 61839.397 | C12: =C10/C11 -> 66634.898 | D12: =D10/D11 -> 71667.893 | E12: =D12*(1+E13) -> 77153.303 | F12: =E12*(1+F13) -> 83058.562 | G12: =F12*(1+G13) -> 89415.806 | H12: =G12*(1+H13) -> 96259.629
A13: Growth % | C13: =C12/B12-1 -> 0.077547672 | D13: =D12/C12-1 -> 0.075530918 | E13: =AVERAGE($C$13:$D$13) -> 0.076539295 | F13: =AVERAGE($C$13:$D$13) -> 0.076539295 | G13: =AVERAGE($C$13:$D$13) -> 0.076539295 | H13: =AVERAGE($C$13:$D$13) -> 0.076539295
A16: Europe, Middle East, and Africa (EMEA) (in thousands) | I16: Average Monthly Revenues
A17: Revenues | B17: 3963707 | C17: 5543067 | D17: 7772252 | E17: =E19*E18 -> 9981422.6 | F17: =F19*F18 -> 12088960 | G17: =G19*G18 -> 13432600 | H17: =H19*H18 -> 14656928 | I17: 2018 | J17: 2019 | K17: 2020
A18: Average yearly revenue per membership | B18: =I18*12 -> 125.4 | C18: =J18*12 -> 123.96 | D18: =K18*12 -> 128.64 | E18: =AVERAGE(B18:D18) -> 126 | F18: =AVERAGE(E18) -> 126 | G18: =AVERAGE(F18) -> 126 | H18: =AVERAGE(G18) -> 126 | I18: 10.45 | J18: 10.33 | K18: 10.72
A19: Average no of Paid membership | B19: =B17/B18 -> 31608.509 | C19: =C17/C18 -> 44716.578 | D19: =D17/D18 -> 60418.626 | E19: =D19*(1+E20) -> 79217.64 | F19: =E19*(1+F20) -> 95944.128 | G19: =F19*(1+G20) -> 106607.93 | H19: =G19*(1+H20) -> 116324.82
A20: Growth % | C20: =C19/B19-1 -> 0.41470065 | D20: =D19/C19-1 -> 0.351146 | E20: =D20-4% -> 0.311146 | F20: =E20-10% -> 0.211146 | G20: =F20-10% -> 0.111146 | H20: =G20-2% -> 0.091146005
A23: Latin America (LATAM) (in thousands) | I23: Average Monthly Revenues
A24: Revenues | B24: 2237697 | C24: 2795434 | D24: 3156727 | E24: =E26*E25 -> 3842573.8 | F24: =F26*F25 -> 4429558.5 | G24: =G26*G25 -> 4995470.9 | H24: =H26*H25 -> 5508796.6 | I24: 2018 | J24: 2019 | K24: 2020
A25: Average yearly revenue per membership | B25: =I25*12 -> 111.96 | C25: =J25*12 -> 110.88 | D25: =K25*12 -> 109.44 | E25: =AVERAGE($B$25:$D$25) -> 110.76 | F25: =AVERAGE($B$25:$D$25) -> 110.76 | G25: =AVERAGE($B$25:$D$25) -> 110.76 | H25: =AVERAGE($B$25:$D$25) -> 110.76 | I25: 9.33 | J25: 9.24 | K25: 9.12
A26: Average Paid membership | B26: =B24/B25 -> 19986.576 | C26: =C24/C25 -> 25211.346 | D26: =D24/D25 -> 28844.362 | E26: =D26*(1+E27) -> 34692.793 | F26: =E26*(1+F27) -> 39992.402 | G26: =F26*(1+G27) -> 45101.76 | H26: =G26*(1+H27) -> 49736.336
A27: Growth % | C27: =C26/B26-1 -> 0.26141397 | D27: =D26/C26-1 -> 0.14410245 | E27: =AVERAGE(C27:D27) -> 0.20275821 | F27: =E27-5% -> 0.15275821 | G27: =F27-2.5% -> 0.12775821 | H27: =G27-2.5% -> 0.10275821
A30: Asia-Pacific (in thousands) | I30: Average Monthly Revenues
A31: Revenues | B31: 945816 | C31: 1469521 | D31: 2372300 | E31: =E33*E32 -> 3192485.3 | F31: =F33*F32 -> 4633674.1 | G31: =G33*G32 -> 6493777.2 | H31: =H33*H32 -> 8451206.7 | I31: 2018 | J31: 2019 | K31: 2020
A32: Average yearly revenue per membership | B32: =I32*12 -> 133.92 | C32: =J32*12 -> 150.84 | D32: =K32*12 -> 159.84 | E32: =AVERAGE(B32:D32) -> 148.2 | F32: =E32 -> 148.2 | G32: =F32 -> 148.2 | H32: =G32 -> 148.2 | I32: 11.16 | J32: 12.57 | K32: 13.32
A33: Average Paid membership | B33: =B31/B32 -> 7062.5448 | C33: =C31/C32 -> 9742.2501 | D33: =D31/D32 -> 14841.717 | E33: =D33*(1+E34) -> 21541.736 | F33: =E33*(1+F34) -> 31266.357 | G33: =F33*(1+G34) -> 43817.66 | H33: =G33*(1+H34) -> 57025.686
A34: Growth % | C34: =C33/B33-1 -> 0.37942489 | D34: =D33/C33-1 -> 0.52343828 | E34: =AVERAGE(C34:D34) -> 0.45143159 | F34: =E34 -> 0.45143159 | G34: =F34-5% -> 0.40143159 | H34: =G34-10% -> 0.30143159

Sheet Other Items
A1: Other Items
A3: (in thousands) | B3: 2018 Act | C3: 2019 Act | D3: 2020 Act | E3: 2021 Forcasted | F3: 2022 Forcasted | G3: 2023 Forcasted | H3: 2024 Forcasted
A4: Cost of Goods Sold | B4: ='P&L Input'!B4-Schedules!B6 -> 9884381 | C4: ='P&L Input'!C4-Schedules!C6 -> 12336634 | D4: ='P&L Input'!D4-Schedules!D6 -> 15160609 | E4: =E5*'Revenue Modelling'!E6 -> 17610348 | F4: =F5*'Revenue Modelling'!F6 -> 20668053 | G4: =G5*'Revenue Modelling'!G6 -> 23546403 | H4: =H5*'Revenue Modelling'!H6 -> 26426739 | J4: NOTES
A5: as a % revenues | B5: =B4/'P&L Input'!B3 -> 0.62581788 | C5: =C4/'P&L Input'!C3 -> 0.61204408 | D5: =D4/'P&L Input'!D3 -> 0.60652004 | E5: =AVERAGE($B$5:$D$5) -> 0.614794 | F5: =AVERAGE($B$5:$D$5) -> 0.614794 | G5: =AVERAGE($B$5:$D$5) -> 0.614794 | H5: =AVERAGE($B$5:$D$5) -> 0.614794
A7: Marketing | B7: ='P&L Input'!B5 -> 2369469 | C7: ='P&L Input'!C5 -> 2652462 | D7: ='P&L Input'!D5 -> 2228362 | E7: =E8*'Revenue Modelling'!E6 -> 3540077.3 | F7: =F8*'Revenue Modelling'!F6 -> 4154744.9 | G7: =G8*'Revenue Modelling'!G6 -> 4733358.3 | H7: =H8*'Revenue Modelling'!H6 -> 5312370.7
A8: as a % revenues | B8: =B7/'P&L Input'!B3 -> 0.15002012 | C8: =C7/'P&L Input'!C3 -> 0.13159373 | D8: =D7/'P&L Input'!D3 -> 0.089148544 | E8: =AVERAGE($B$8:$D$8) -> 0.12358747 | F8: =AVERAGE($B$8:$D$8) -> 0.12358747 | G8: =AVERAGE($B$8:$D$8) -> 0.12358747 | H8: =AVERAGE($B$8:$D$8) -> 0.12358747 | J8: Excluding 2018 since marketing spend should be on the lesser side as Market Penetration Increases but still high enough to capture untapped markets
A10: Technology and Development | B10: ='P&L Input'!B6 -> 1221814 | C10: ='P&L Input'!C6 -> 1545149 | D10: ='P&L Input'!D6 -> 1829600 | E10: =E11*'Revenue Modelling'!E6 -> 2169434.5 | F10: =F11*'Revenue Modelling'!F6 -> 2546115.8 | G10: =G11*'Revenue Modelling'!G6 -> 2900702.4 | H10: =H11*'Revenue Modelling'!H6 -> 3255533.5
A11: as a % revenues | B11: =B10/'P&L Input'!B3 -> 0.077357707 | C11: =C10/'P&L Input'!C3 -> 0.076657806 | D11: =D10/'P&L Input'!D3 -> 0.073195547 | E11: =AVERAGE($B$11:$D$11) -> 0.07573702 | F11: =AVERAGE($B$11:$D$11) -> 0.07573702 | G11: =AVERAGE($B$11:$D$11) -> 0.07573702 | H11: =AVERAGE($B$11:$D$11) -> 0.07573702
A13: General and Administrative | B13: ='P&L Input'!B7 -> 630294 | C13: ='P&L Input'!C7 -> 914369 | D13: ='P&L Input'!D7 -> 1076486 | E13: =E14*'Revenue Modelling'!E6 -> 1225366.7 | F13: =F14*'Revenue Modelling'!F6 -> 1438128.5 | G13: =G14*'Revenue Modelling'!G6 -> 1638410.5 | H13: =H14*'Revenue Modelling'!H6 -> 1838830.5
A14: as a % revenues | B14: =B13/'P&L Input'!B3 -> 0.039906318 | C14: =C13/'P&L Input'!C3 -> 0.0453636 | D14: =D13/'P&L Input'!D3 -> 0.043066234 | E14: =AVERAGE($B$14:$D$14) -> 0.042778718 | F14: =AVERAGE($B$14:$D$14) -> 0.042778718 | G14: =AVERAGE($B$14:$D$14) -> 0.042778718 | H14: =AVERAGE($B$14:$D$14) -> 0.042778718
A16: Other Current assets | B16: ='Balance Sheet Input'!B7 -> 5899652 | C16: ='Balance Sheet Input'!C7 -> 1160067 | D16: ='Balance Sheet Input'!D7 -> 1556030 | E16: =E17*'Revenue Modelling'!E6 -> 1783137.4 | F16: =F17*'Revenue Modelling'!F6 -> 2092745.5 | G16: =G17*'Revenue Modelling'!G6 -> 2384193.1 | H16: =H17*'Revenue Modelling'!H6 -> 2675841.8
A17: as a % revenues | B17: =B16/'P&L Input'!B3 -> 0.37352948 | C17: =C16/'P&L Input'!C3 -> 0.057553149 | D17: =D16/'P&L Input'!D3 -> 0.062251021 | E17: =$D$17 -> 0.062251021 | F17: =$D$17 -> 0.062251021 | G17: =$D$17 -> 0.062251021 | H17: =$D$17 -> 0.062251021
A19: Accounts Payable | B19: ='Balance Sheet Input'!B17 -> 562985 | C19: ='Balance Sheet Input'!C17 -> 674347 | D19: ='Balance Sheet Input'!D17 -> 656183 | E19: =(E20*E4)/365 -> 762212.85 | F19: =(F20*F4)/365 -> 894556.74 | G19: =(G20*G4)/365 -> 1019137.8 | H19: =(H20*H4)/365 -> 1143804.8 | J19: Being Cautious with the Days Payable and Estimating it on the higher side and then slowly declining
A20: Days Payable | B20: =(B19/'Other Items'!B4)*365 -> 20.789316 | C20: =(C19/'Other Items'!C4)*365 -> 19.951687 | D20: =(D19/'Other Items'!D4)*365 -> 15.797967 | E20: =$D$20 -> 15.797967 | F20: =$D$20 -> 15.797967 | G20: =$D$20 -> 15.797967 | H20: =$D$20 -> 15.797967
A22: Accrued Expenses and other Liabilities | B22: ='Balance Sheet Input'!B18 -> 481874 | C22: ='Balance Sheet Input'!C18 -> 843043 | D22: ='Balance Sheet Input'!D18 -> 1102196 | E22: =E23*'Revenue Modelling'!E6 -> 1111676.6 | F22: =F23*'Revenue Modelling'!F6 -> 1304698.2 | G22: =G23*'Revenue Modelling'!G6 -> 1486397.9 | H22: =H23*'Revenue Modelling'!H6 -> 1668222.9
A23: as a % revenues | B23: =B22/'P&L Input'!B3 -> 0.030509282 | C23: =C22/'P&L Input'!C3 -> 0.04182498 | D23: =D22/'P&L Input'!D3 -> 0.044094796 | E23: =AVERAGE($B$23:$D$23) -> 0.038809686 | F23: =AVERAGE($B$23:$D$23) -> 0.038809686 | G23: =AVERAGE($B$23:$D$23) -> 0.038809686 | H23: =AVERAGE($B$23:$D$23) -> 0.038809686
A25: Deferred Revenue | B25: ='Balance Sheet Input'!B19 -> 760899 | C25: ='Balance Sheet Input'!C19 -> 924745 | D25: ='Balance Sheet Input'!D19 -> 1117992 | E25: =E26*'Revenue Modelling'!E6 -> 1325090.7 | F25: =F26*'Revenue Modelling'!F6 -> 1555167.7 | G25: =G26*'Revenue Modelling'!G6 -> 1771749.2 | H25: =H26*'Revenue Modelling'!H6 -> 1988480
A26: as a % revenues | B26: =B25/'P&L Input'!B3 -> 0.048175419 | C26: =C25/'P&L Input'!C3 -> 0.045878373 | D26: =D25/'P&L Input'!D3 -> 0.044726736 | E26: =AVERAGE($B$26:$D$26) -> 0.046260176 | F26: =AVERAGE($B$26:$D$26) -> 0.046260176 | G26: =AVERAGE($B$26:$D$26) -> 0.046260176 | H26: =AVERAGE($B$26:$D$26) -> 0.046260176

Sheet Schedules
A1: PP&E
A3: (in thousands) | B3: 2018 Act | C3: 2019 Act | D3: 2020 Act | E3: 2021 Forcasted | F3: 2022 Forcasted | G3: 2023 Forcasted | H3: 2024 Forcasted
A4: Beginning Balance | C4: =B7 -> 418281 | D4: =C7 -> 565221 | E4: =D7 -> 960183 | F4: =E7 -> 1284140.1 | G4: =F7 -> 1580571.3 | H4: =G7 -> 1855677.9 | I4: Assumption
A5: add: Capex | C5: =C7+C6-C4 -> 250519 | D5: =D7+D6-D4 -> 510672 | E5: 510672 | F5: 510672 | G5: 510672 | H5: 510672 | I5: Cap Exp - Beginning of Year
A6: less: Depreciation | B6: 83157 | C6: 103579 | D6: 115710 | E6: =(E4+E5)/E9 -> 186714.87 | F6: =(F4+F5)/F9 -> 214240.79 | G6: =(G4+G5)/G9 -> 235565.47 | H6: =(H4+H5)/H9 -> 252342.12
A7: Closing Balance | B7: ='Balance Sheet Input'!B10 -> 418281 | C7: ='Balance Sheet Input'!C10 -> 565221 | D7: ='Balance Sheet Input'!D10 -> 960183 | E7: =E4+E5-E6 -> 1284140.1 | F7: =F4+F5-F6 -> 1580571.3 | G7: =G4+G5-G6 -> 1855677.9 | H7: =H4+H5-H6 -> 2114007.8
A9: Useful life | C9: =(C4+C5)/C6 -> 6.4569073 | D9: =(D4+D5)/D6 -> 9.2981851 | E9: =AVERAGE($C$9:$D$9) -> 7.8775462 | F9: =E9+0.5 -> 8.3775462 | G9: =F9+0.5 -> 8.8775462 | H9: =G9+0.5 -> 9.3775462 | I9: Continuous Increment Since Life Seems Low
A12: Content Assets
A13: (in thousands) | B13: 2018 Act | C13: 2019 Act | D13: 2020 Act | E13: 2021 Forcasted | F13: 2022 Forcasted | G13: 2023 Forcasted | H13: 2024 Forcasted
A14: Beginning Balance | C14: =B17 -> 14951141 | D14: =C17 -> 24504567 | E14: =D17 -> 25383950 | F14: =E17 -> 26490395 | G14: =F17 -> 27281060 | H14: =G17 -> 27846069
A15: add: Addition to Content Assets | C15: =C17+C16-C14 -> 18769673 | D15: =D17+D16-D14 -> 11686295 | E15: 11686295 | F15: 11686295 | G15: 11686295 | H15: 11686295
A16: less: Amortisation of Content Assets | C16: 9216247 | D16: 10806912 | E16: =(E14+E15)/E19 -> 10579850 | F16: =(F14+F15)/F19 -> 10895630 | G16: =(G14+G15)/G19 -> 11121286 | H16: =(H14+H15)/H19 -> 11282539
A17: Closing Balance | B17: ='Balance Sheet Input'!B9 -> 14951141 | C17: ='Balance Sheet Input'!C9 -> 24504567 | D17: ='Balance Sheet Input'!D9 -> 25383950 | E17: =E14+E15-E16 -> 26490395 | F17: =F14+F15-F16 -> 27281060 | G17: =G14+G15-G16 -> 27846069 | H17: =H14+H15-H16 -> 28249825
A19: Useful life | C19: =(C14+C15)/C16 -> 3.6588444 | D19: =(D14+D15)/D16 -> 3.3488625 | E19: =AVERAGE($C$19:$D$19) -> 3.5038534 | F19: =AVERAGE($C$19:$D$19) -> 3.5038534 | G19: =AVERAGE($C$19:$D$19) -> 3.5038534 | H19: =AVERAGE($C$19:$D$19) -> 3.5038534
A22: Debt Schedule | I22: Assumption
A23: Beginning Balance of Debt | C23: =B25 -> 10360058 | D23: =C25 -> 14759260 | E23: =D25 -> 15809095 | F23: =E25 -> 15309095 | G23: =F25 -> 14609095 | H23: =G25 -> 14609095 | I23: No additional Debt is taken since already high debt
A24: add/less: Debt Taken /(debt repaid) | C24: =C25-C23 -> 4399202 | D24: =D25-D23 -> 1049835 | E24: =-500000 -> -500000 | F24: -700000 | G24: 0 | H24: -400000 | I24: Taken from the Table
A25: Closing Balance | B25: ='Balance Sheet Input'!B23 -> 10360058 | C25: ='Balance Sheet Input'!C23 -> 14759260 | D25: ='Balance Sheet Input'!D23 -> 15809095 | E25: =E23+E24 -> 15309095 | F25: =F23+F24 -> 14609095 | G25: =G23+G24 -> 14609095 | H25: =H23+H24 -> 14209095
A27: Interest Expense | B27: ='P&L Input'!B10 -> -420493 | C27: ='P&L Input'!C10 -> -626023 | D27: ='P&L Input'!D10 -> -767499 | E27: =E25*E28 -> -696284.81 | F27: =F25*F28 -> -664447.57 | G27: =G25*G28 -> -664447.57 | H27: =H25*H28 -> -646254.86
B28: =B27/B25 -> -0.0405879 | C28: =C27/C25 -> -0.042415609 | D28: =D27/D25 -> -0.04854794 | E28: =AVERAGE($C$28:$D$28) -> -0.045481775 | F28: =AVERAGE($C$28:$D$28) -> -0.045481775 | G28: =AVERAGE($C$28:$D$28) -> -0.045481775 | H28: =AVERAGE($C$28:$D$28) -> -0.045481775

Sheet P&L
A1: P&L Forcasting
A3: (in thousands) | B3: 2018 Act | C3: 2019 Act | D3: 2020 Act | E3: 2021 Forcasted | F3: 2022 Forcasted | G3: 2023 Forcasted | H3: 2024 Forcasted
A4: Streaming revenues | B4: ='Revenue Modelling'!B3 -> 15428752 | C4: ='Revenue Modelling'!C3 -> 19859230 | D4: ='Revenue Modelling'!D3 -> 24756675 | E4: ='Revenue Modelling'!E3 -> 28450601 | F4: ='Revenue Modelling'!F3 -> 33461472 | G4: ='Revenue Modelling'!G3 -> 38173270 | H4: ='Revenue Modelling'!H3 -> 42882608
A5: DVD Revenues | B5: ='Revenue Modelling'!B4 -> 365589 | C5: ='Revenue Modelling'!C4 -> 297217 | D5: ='Revenue Modelling'!D4 -> 239381 | E5: ='Revenue Modelling'!E4 -> 193705.84 | F5: ='Revenue Modelling'!F4 -> 156379 | G5: ='Revenue Modelling'!G4 -> 126393.03 | H5: ='Revenue Modelling'!H4 -> 102097.1
A6: Total Revenues | B6: =SUM(B4:B5) -> 15794341 | C6: =SUM(C4:C5) -> 20156447 | D6: =SUM(D4:D5) -> 24996056 | E6: =SUM(E4:E5) -> 28644307 | F6: =SUM(F4:F5) -> 33617851 | G6: =SUM(G4:G5) -> 38299663 | H6: =SUM(H4:H5) -> 42984705
A7: Cost of Goods Sold | B7: ='Other Items'!B4 -> 9884381 | C7: ='Other Items'!C4 -> 12336634 | D7: ='Other Items'!D4 -> 15160609 | E7: ='Other Items'!E4 -> 17610348 | F7: ='Other Items'!F4 -> 20668053 | G7: ='Other Items'!G4 -> 23546403 | H7: ='Other Items'!H4 -> 26426739
A8: Gross Margin | B8: =B6-B7 -> 5909960 | C8: =C6-C7 -> 7819813 | D8: =D6-D7 -> 9835447 | E8: =E6-E7 -> 11033959 | F8: =F6-F7 -> 12949798 | G8: =G6-G7 -> 14753260 | H8: =H6-H7 -> 16557966
A9: Operating Expenses
A10: Marketing | B10: ='Other Items'!B7 -> 2369469 | C10: ='Other Items'!C7 -> 2652462 | D10: ='Other Items'!D7 -> 2228362 | E10: ='Other Items'!E7 -> 3540077.3 | F10: ='Other Items'!F7 -> 4154744.9 | G10: ='Other Items'!G7 -> 4733358.3 | H10: ='Other Items'!H7 -> 5312370.7
A11: Technology and development | B11: ='Other Items'!B10 -> 1221814 | C11: ='Other Items'!C10 -> 1545149 | D11: ='Other Items'!D10 -> 1829600 | E11: ='Other Items'!E10 -> 2169434.5 | F11: ='Other Items'!F10 -> 2546115.8 | G11: ='Other Items'!G10 -> 2900702.4 | H11: ='Other Items'!H10 -> 3255533.5
A12: General and administrative | B12: ='Other Items'!B13 -> 630294 | C12: ='Other Items'!C13 -> 914369 | D12: ='Other Items'!D13 -> 1076486 | E12: ='Other Items'!E13 -> 1225366.7 | F12: ='Other Items'!F13 -> 1438128.5 | G12: ='Other Items'!G13 -> 1638410.5 | H12: ='Other Items'!H13 -> 1838830.5
A13: EBITDA | B13: =B8-SUM(B10:B12) -> 1688383 | C13: =C8-SUM(C10:C12) -> 2707833 | D13: =D8-SUM(D10:D12) -> 4700999 | E13: =E8-SUM(E10:E12) -> 4099080.4 | F13: =F8-SUM(F10:F12) -> 4810808.4 | G13: =G8-SUM(G10:G12) -> 5480788.9 | H13: =H8-SUM(H10:H12) -> 6151231.5
A14: less: Depreciation | B14: =Schedules!B6 -> 83157 | C14: =Schedules!C6 -> 103579 | D14: =Schedules!D6 -> 115710 | E14: =Schedules!E6 -> 186714.87 | F14: =Schedules!F6 -> 214240.79 | G14: =Schedules!G6 -> 235565.47 | H14: =Schedules!H6 -> 252342.12
A15: EBIT | B15: =B13-B14 -> 1605226 | C15: =C13-C14 -> 2604254 | D15: =D13-D14 -> 4585289 | E15: =E13-E14 -> 3912365.6 | F15: =F13-F14 -> 4596567.6 | G15: =G13-G14 -> 5245223.5 | H15: =H13-H14 -> 5898889.4
A16: Interest | B16: =Schedules!B27 -> -420493 | C16: =Schedules!C27 -> -626023 | D16: =Schedules!D27 -> -767499 | E16: =Schedules!E27 -> -696284.81 | F16: =Schedules!F27 -> -664447.57 | G16: =Schedules!G27 -> -664447.57 | H16: =Schedules!H27 -> -646254.86
A17: Interest and other income (expense) | B17: ='P&L Input'!B11 -> 41725 | C17: ='P&L Input'!C11 -> 84000 | D17: ='P&L Input'!D11 -> -618441 | E17: 0 | F17: 0 | G17: 0 | H17: 0 | I17: 0 because very insignificant and cannot predict
A18: EBT | B18: =B15+B16+B17 -> 1226458 | C18: =C15+C16+C17 -> 2062231 | D18: =D15+D16+D17 -> 3199349 | E18: =E15+E16+E17 -> 3216080.8 | F18: =F15+F16+F17 -> 3932120.1 | G18: =G15+G16+G17 -> 4580775.9 | H18: =H15+H16+H17 -> 5252634.5
A19: Taxes | B19: ='P&L Input'!B13 -> -15216 | C19: ='P&L Input'!C13 -> -195315 | D19: ='P&L Input'!D13 -> -437954 | E19: =E20*E18 -> -440244.39 | F19: =F20*F18 -> -538261.91 | G19: =G20*G18 -> -627055.42 | H19: =H20*H18 -> -719025.12
A20: tax rate % | B20: =B19/B18 -> -0.012406458 | C20: =C19/C18 -> -0.094710534 | D20: =D19/D18 -> -0.13688847 | E20: =$D$20 -> -0.13688847 | F20: =$D$20 -> -0.13688847 | G20: =$D$20 -> -0.13688847 | H20: =$D$20 -> -0.13688847 | I20: Prudence
A21: Net Income | B21: =B18+B19 -> 1211242 | C21: =C18+C19 -> 1866916 | D21: =D18+D19 -> 2761395 | E21: =E18+E19 -> 2775836.4 | F21: =F18+F19 -> 3393858.2 | G21: =G18+G19 -> 3953720.5 | H21: =H18+H19 -> 4533609.4

Sheet Balance Sheet
A1: Balance Sheet
A3: (in thousands) | B3: 2018 Act | C3: 2019 Act | D3: 2020 Act | E3: 2021 Forcasted | F3: 2022 Forcasted | G3: 2023 Forcasted | H3: 2024 Forcasted
A4: Assets
A5: Current assets:
A6: Cash and cash equivalents | B6: 3794483 | C6: 5018437 | D6: 8205550 | E6: =D6+'Cashflow Statement'!E25 -> 9146486.3 | F6: =E6+'Cashflow Statement'!F25 -> 10999082 | G6: =F6+'Cashflow Statement'!G25 -> 14344102 | H6: =G6+'Cashflow Statement'!H25 -> 18047200
A7: Other current assets | B7: =748466+5151186 -> 5899652 | C7: 1160067 | D7: 1556030 | E7: ='Other Items'!E16 -> 1783137.4 | F7: ='Other Items'!F16 -> 2092745.5 | G7: ='Other Items'!G16 -> 2384193.1 | H7: ='Other Items'!H16 -> 2675841.8
A8: Total current assets | B8: =SUM(B6:B7) -> 9694135 | C8: =SUM(C6:C7) -> 6178504 | D8: =SUM(D6:D7) -> 9761580 | E8: =SUM(E6:E7) -> 10929624 | F8: =SUM(F6:F7) -> 13091828 | G8: =SUM(G6:G7) -> 16728295 | H8: =SUM(H6:H7) -> 20723041
A9: Content assets, net | B9: 14951141 | C9: 24504567 | D9: 25383950 | E9: =Schedules!E17 -> 26490395 | F9: =Schedules!F17 -> 27281060 | G9: =Schedules!G17 -> 27846069 | H9: =Schedules!H17 -> 28249825
A10: Property and equipment, net | B10: 418281 | C10: 565221 | D10: 960183 | E10: =Schedules!E7 -> 1284140.1 | F10: =Schedules!F7 -> 1580571.3 | G10: =Schedules!G7 -> 1855677.9 | H10: =Schedules!H7 -> 2114007.8
A11: Other non-current assets | B11: 910843 | C11: 2727420 | D11: 3174646 | E11: =D11 -> 3174646 | F11: =E11 -> 3174646 | G11: =F11 -> 3174646 | H11: =G11 -> 3174646
A12: Total assets | B12: =SUM(B8:B11) -> 25974400 | C12: =SUM(C8:C11) -> 33975712 | D12: =SUM(D8:D11) -> 39280359 | E12: =SUM(E8:E11) -> 41878804 | F12: =SUM(F8:F11) -> 45128105 | G12: =ROUND(SUM(G8:G11),3) -> 49604688 | H12: =ROUND(SUM(H8:H11),3) -> 54261520
A14: Liabilities and Stockholders' Equity
A15: Current liabilities:
A16: Current content liabilities | B16: 4681562 | C16: 4413561 | D16: 4429536 | E16: =D16 -> 4429536 | F16: =E16 -> 4429536 | G16: =F16 -> 4429536 | H16: =G16 -> 4429536
A17: Accounts payable | B17: 562985 | C17: 674347 | D17: 656183 | E17: ='Other Items'!E19 -> 762212.85 | F17: ='Other Items'!F19 -> 894556.74 | G17: ='Other Items'!G19 -> 1019137.8 | H17: ='Other Items'!H19 -> 1143804.8
A18: Accrued expenses and other liabilities | B18: 481874 | C18: 843043 | D18: 1102196 | E18: ='Other Items'!E22 -> 1111676.6 | F18: ='Other Items'!F22 -> 1304698.2 | G18: ='Other Items'!G22 -> 1486397.9 | H18: ='Other Items'!H22 -> 1668222.9
A19: Deferred revenue | B19: 760899 | C19: 924745 | D19: 1117992 | E19: ='Other Items'!E25 -> 1325090.7 | F19: ='Other Items'!F25 -> 1555167.7 | G19: ='Other Items'!G25 -> 1771749.2 | H19: ='Other Items'!H25 -> 1988480
A20: Short-term debt | B20: 0 | C20: 0 | D20: 499878 | E20: =D20 -> 499878 | F20: =E20 -> 499878 | G20: =F20 -> 499878 | H20: =G20 -> 499878
A21: Total current liabilities | B21: =SUM(B16:B20) -> 6487320 | C21: =SUM(C16:C20) -> 6855696 | D21: =SUM(D16:D20) -> 7805785 | E21: =SUM(E16:E20) -> 8128394.1 | F21: =SUM(F16:F20) -> 8683836.7 | G21: =SUM(G16:G20) -> 9206698.9 | H21: =SUM(H16:H20) -> 9729921.7
A22: Non-current content liabilities | B22: 3759026 | C22: 3334323 | D22: 2618084 | E22: =D22 -> 2618084 | F22: =E22 -> 2618084 | G22: =F22 -> 2618084 | H22: =G22 -> 2618084
A23: Long-term debt | B23: 10360058 | C23: 14759260 | D23: 15809095 | E23: =Schedules!E25 -> 15309095 | F23: =Schedules!F25 -> 14609095 | G23: =Schedules!G25 -> 14609095 | H23: =Schedules!H25 -> 14209095
A24: Other non-current liabilities | B24: 129231 | C24: 1444276 | D24: 1982155 | E24: =D24 -> 1982155 | F24: =E24 -> 1982155 | G24: =F24 -> 1982155 | H24: =G24 -> 1982155
A25: Total liabilities | B25: =SUM(B21:B24) -> 20735635 | C25: =SUM(C21:C24) -> 26393555 | D25: =SUM(D21:D24) -> 28215119 | E25: =SUM(E21:E24) -> 28037728 | F25: =SUM(F21:F24) -> 27893171 | G25: =SUM(G21:G24) -> 28416033 | H25: =SUM(H21:H24) -> 28539256
A26: Stockholders' equity:
A27: Common stock | B27: 2315988 | C27: 2793929 | D27: 3447698 | E27: =D27 -> 3447698 | F27: =E27 -> 3447698 | G27: =F27 -> 3447698 | H27: =G27 -> 3447698
A28: Treasury stock | C28: 0 | D28: 0 | E28: =D28 -> 0 | F28: =E28 -> 0 | G28: =F28 -> 0 | H28: =G28 -> 0
A29: Accumulated other comprehensive income (loss) | B29: -19582 | C29: -23521 | D29: 44398 | E29: =D29 -> 44398 | F29: =E29 -> 44398 | G29: =F29 -> 44398 | H29: =G29 -> 44398
A30: Retained earnings | B30: 2942359 | C30: 4811749 | D30: 7573144 | E30: =D30+'P&L'!E21 -> 10348980 | F30: =E30+'P&L'!F21 -> 13742839 | G30: =F30+'P&L'!G21 -> 17696559 | H30: =G30+'P&L'!H21 -> 22230168
A31: Total stockholders' equity | B31: =SUM(B27:B30) -> 5238765 | C31: =SUM(C27:C30) -> 7582157 | D31: =SUM(D27:D30) -> 11065240 | E31: =SUM(E27:E30) -> 13841076 | F31: =SUM(F27:F30) -> 17234935 | G31: =SUM(G27:G30) -> 21188655 | H31: =SUM(H27:H30) -> 25722264
A32: Total liabilities and stockholders' equity | B32: =B25+B31 -> 25974400 | C32: =C25+C31 -> 33975712 | D32: =D25+D31 -> 39280359 | E32: =E25+E31 -> 41878804 | F32: =F25+F31 -> 45128105 | G32: =ROUND(G25+G31,3) -> 49604688 | H32: =ROUND(H25+H31,3) -> 54261520
A35: Check | B35: =B32=B12 -> TRUE | C35: =C32=C12 -> TRUE | D35: =D32=D12 -> TRUE | E35: =E32=E12 -> TRUE | F35: =F32=F12 -> TRUE | G35: =G32=G12 -> TRUE | H35: =H32=H12 -> TRUE

Sheet Cashflow Statement
A1: Cash Flow
A3: (in thousands) | B3: 2018 Act | C3: 2019 Act | D3: 2020 Act | E3: 2021 Forcasted | F3: 2022 Forcasted | G3: 2023 Forcasted | H3: 2024 Forcasted
A4: EBIT | E4: ='P&L'!E15 -> 3912365.6 | F4: ='P&L'!F15 -> 4596567.6 | G4: ='P&L'!G15 -> 5245223.5 | H4: ='P&L'!H15 -> 5898889.4
A5: Operating Taxes | E5: =E6*E4 -> -535557.75 | F5: =F6*F4 -> -629217.13 | G5: =G6*G4 -> -718010.63 | H5: =H6*H4 -> -807489.96
A6: Tax Rate % | E6: -0.13688847 | F6: -0.13688847 | G6: -0.13688847 | H6: -0.13688847
A7: NOPAT | E7: =E4+E5 -> 3376807.8 | F7: =F4+F5 -> 3967350.5 | G7: =G4+G5 -> 4527212.8 | H7: =H4+H5 -> 5091399.4
A8: add Amortization | E8: =Schedules!E16 -> 10579850 | F8: =Schedules!F16 -> 10895630 | G8: =Schedules!G16 -> 11121286 | H8: =Schedules!H16 -> 11282539
A9: add Depreciation | E9: =Schedules!E6 -> 186714.87 | F9: =Schedules!F6 -> 214240.79 | G9: =Schedules!G6 -> 235565.47 | H9: =Schedules!H6 -> 252342.12
A10: Gross Cash Flow | E10: =E7+E8+E9 -> 14143373 | F10: =F7+F8+F9 -> 15077221 | G10: =G7+G8+G9 -> 15884064 | H10: =H7+H8+H9 -> 16626281
A11: Account Payables | E11: ='Other Items'!E19-'Other Items'!D19 -> 106029.85 | F11: ='Other Items'!F19-'Other Items'!E19 -> 132343.88 | G11: ='Other Items'!G19-'Other Items'!F19 -> 124581.05 | H11: ='Other Items'!H19-'Other Items'!G19 -> 124666.97
A12: Deferred Revenue | E12: ='Other Items'!E25-'Other Items'!D25 -> 207098.69 | F12: ='Other Items'!F25-'Other Items'!E25 -> 230077 | G12: ='Other Items'!G25-'Other Items'!F25 -> 216581.48 | H12: ='Other Items'!H25-'Other Items'!G25 -> 216730.85
A13: Current content liabilites | E13: =-E13 -> 0
A14: Accrued expenses and other liabilities | E14: ='Other Items'!E22-'Other Items'!D22 -> 9480.5674 | F14: ='Other Items'!F22-'Other Items'!E22 -> 193021.66 | G14: ='Other Items'!G22-'Other Items'!F22 -> 181699.68 | H14: ='Other Items'!H22-'Other Items'!G22 -> 181824.99
A15: Other current assets | E15: =-('Other Items'!E16-'Other Items'!D16) -> -227107.35 | F15: =-('Other Items'!F16-'Other Items'!E16) -> -309608.16 | G15: =-('Other Items'!G16-'Other Items'!F16) -> -291447.62 | H15: =-('Other Items'!H16-'Other Items'!G16) -> -291648.62
A16: Investments in Working Capital | E16: =E11+E12+E14+E15 -> 95501.762 | F16: =F11+F12+F14+F15 -> 245834.38 | G16: =G11+G12+G14+G15 -> 231414.59 | H16: =H11+H12+H14+H15 -> 231574.19
A17: Content Assets | E17: =Schedules!E15 -> 11686295 | F17: =Schedules!F15 -> 11686295 | G17: =Schedules!G15 -> 11686295 | H17: =Schedules!H15 -> 11686295
A18: PP&E | E18: =Schedules!E5 -> 510672 | F18: =Schedules!F5 -> 510672 | G18: =Schedules!G5 -> 510672 | H18: =Schedules!H5 -> 510672
A19: Capex: | E19: =-(E17+E18) -> -12196967 | F19: =-(F17+F18) -> -12196967 | G19: =-(G17+G18) -> -12196967 | H19: =-(H17+H18) -> -12196967
A20: Extraordinary Items
A21: UFCF | E21: =E19+E16+E10 -> 2041907.8 | F21: =F19+F16+F10 -> 3126088.4 | G21: =G19+G16+G10 -> 3918511.5 | H21: =H19+H16+H10 -> 4660888.1
A22: Debt taken (Repaid) | E22: =Schedules!E24 -> -500000 | F22: =Schedules!F24 -> -700000 | G22: =Schedules!G24 -> 0 | H22: =Schedules!H24 -> -400000
A23: Interest Expense | E23: ='P&L'!E16 -> -696284.81 | F23: ='P&L'!F16 -> -664447.57 | G23: ='P&L'!G16 -> -664447.57 | H23: ='P&L'!H16 -> -646254.86
A24: Diff b/w Operating Taxes & Actual Taxes | E24: ='P&L'!E19-'Cashflow Statement'!E5 -> 95313.364 | F24: ='P&L'!F19-'Cashflow Statement'!F5 -> 90955.213 | G24: ='P&L'!G19-'Cashflow Statement'!G5 -> 90955.213 | H24: ='P&L'!H19-'Cashflow Statement'!H5 -> 88464.841
A25: Net Cash Flow | E25: =SUM(E21:E24) -> 940936.32 | F25: =SUM(F21:F24) -> 1852596 | G25: =SUM(G21:G24) -> 3345019.2 | H25: =SUM(H21:H24) -> 3703098

Sheet WACC
A1: WACC - Cost Of Equity and Debt
A3: Risk free Rate | B3: 0.0167 | D3: Taken from the Net (Past data)
A4: Market Risk Premium | B4: 0.055
A5: Beta | B5: 1.058 | D5: Volatility with respect to the industry/stock market
A7: (in thousands) | B7: Amount
A9: Cost of Equity | B9: =B3*B5+B4 -> 0.0726686 | D9: RiskfreeRate*beta + Market Risk Premium
A10: Cost Debt | B10: 0.04875 | D10: Taken as Interest paid on latest debt(Taken from Schedule)
A12: Equity | B12: ='Balance Sheet'!H31 -> 25722264
A13: Debt | B13: ='Balance Sheet'!H23 -> 14209095 | D13: Long Term Debt
A15: Equity/(Equity+Debt) | B15: =B12/(B12+B13) -> 0.644162
A16: Debt/(Equity+Debt) | B16: =B13/(B13+B12) -> 0.355838
A18: WACC | B18: =B9*B15+B10*B16 -> 0.064157453
A19: (Discount Rate)

Sheet DCF
A1: DCF Analysis
I2: TERMINAL VALUE CALC
A3: (in thousands) | B3: 2021 Forcasted | C3: 2022 Forcasted | D3: 2023 Forcasted | E3: 2024 Forcasted
A4: UFCF | B4: ='Cashflow Statement'!E21 -> 2041907.8 | C4: ='Cashflow Statement'!F21 -> 3126088.4 | D4: ='Cashflow Statement'!G21 -> 3918511.5 | E4: ='Cashflow Statement'!H21 -> 4660888.1
A5: Discounting Factor | B5: =1/(1+WACC!$B$18)^B6 -> 0.93971056 | C5: =1/(1+WACC!$B$18)^C6 -> 0.88305594 | D5: =1/(1+WACC!$B$18)^D6 -> 0.829817 | E5: =1/(1+WACC!$B$18)^E6 -> 0.7797878 | G5: 1/(1+WACC)^no of years
A6: No of Years | B6: 1 | C6: 2 | D6: 3 | E6: 4
A8: PV of UFCF | B8: =B4*B5 -> 1918802.3 | C8: =C4*C5 -> 2760510.9 | D8: =D4*D5 -> 3251647.5 | E8: =E4*E5 -> 3634503.6
A10: Sum of PV | B10: =SUM(B8:E8) -> 11565464
A12: Terminal Value | B12: =E4*(1+WACC!B3)/(WACC!B18-WACC!B3) -> 99852069 | J12: g = risk free rate
A13: PV of Terminal value | B13: =B12*E5 -> 77863425 | C13: Last Year Discounting Factor
A16: Enterprise Value | B16: =B13+B10 -> 89428889 | C16: Sum of PV
A17: Debt | B17: ='Balance Sheet'!H23 -> 14209095
A18: Cash | B18: ='Balance Sheet'!H6 -> 18047200
A19: Equity Value | B19: =B16+B18-B17 -> 93266994 | C19: EV-Debt+Cash | D19: The Debt gets paid off by the cash
A20: TARGET PRICE | B20: =B19/E22 -> 205.33983
E21: Diluted Shares Outstanding
B22: ` | E22: 454208
